<?xml version="1.0" encoding="UTF-8"?><study id="145998">  <accessState>      </accessState>  <addInfo />  <availability>    <availability id="146008">      <availability>        A - Data and documents are released for academic research and teaching.      </availability>      <language>        en      </language>      <study ref="../.." />    </availability>    <availability id="146009">      <availability>        A - Daten und Dokumente sind für die akademische Forschung und Lehre freigegeben.      </availability>      <language>        de      </language>      <study ref="../.." />    </availability>  </availability>  <classifications>    <classification id="13907">      <identifier>              </identifier>      <language>        en      </language>      <term>        Communication, Public Opinion      </term>      <thesaurus>        ZA Kategorien      </thesaurus>    </classification>    <classification id="13906">      <identifier>              </identifier>      <language>        de      </language>      <term>        Kommunikation, öffentliche Meinung      </term>      <thesaurus>        ZA Kategorien      </thesaurus>    </classification>  </classifications>  <collectionDateFormal />  <collectionDates>    <collectionDate id="146016">      <language>        en      </language>      <period>        04.01.1988      </period>      <study ref="../.." />    </collectionDate>    <collectionDate id="146015">      <language>        en      </language>      <period>        04.01.1988      </period>      <study ref="../.." />    </collectionDate>    <collectionDate id="146014">      <language>        de      </language>      <period>        04.01.1988      </period>      <study ref="../.." />    </collectionDate>  </collectionDates>  <collectionModes>    <collectionMode id="146013">      <language>        de      </language>      <mode>        Mündliche Befragung mit standardisiertem Fragebogen zum Fernsehen in der Vorwoche.      </mode>      <study ref="../.." />    </collectionMode>  </collectionModes>  <controlledKeywords />  <currentVersion>    1.0.0  </currentVersion>  <dataCollectors>    <dataCollector id="146000">      <language>        de      </language>      <name>        Staatliches Komitee für Fernsehen beim Ministerrat der DDR, Abteilung Soziologische Forschung, Berlin      </name>      <study ref="../.." />    </dataCollector>    <dataCollector id="145999">      <language>        en      </language>      <name>              </name>      <study ref="../.." />    </dataCollector>  </dataCollectors>  <dataSets>    <dataSet id="146002">      <fileFormat>        SPSS      </fileFormat>      <numberUnits>        881      </numberUnits>      <numberVariables>        166      </numberVariables>      <resourceType>              </resourceType>      <study ref="../.." />      <unitType>              </unitType>    </dataSet>  </dataSets>  <doi>    doi:10.4232/1.10552  </doi>  <doiProposal>    doi:10.4232/1.10552  </doiProposal>  <dsoffset>      </dsoffset>  <fingerprint>      </fingerprint>  <fingerprintMethod>      </fingerprintMethod>  <freeKeywords />  <issueNumber>      </issueNumber>  <issued>    2011-05-26 00:00:00.0 MESZ  </issued>  <language>      </language>  <links />  <notes>    <note id="146007">      <language>        en      </language>      <study ref="../.." />      <text>              </text>    </note>    <note id="146006">      <language>        de      </language>      <study ref="../.." />      <text>        Der Datenpool zum Fernsehverhalten in der DDR umfasst 464 Studien und deckt einen Zeitraum von 1980-1990 ab. Die Studien sind unter den ZA- Nrn. ZA7000 - ZA7462 archiviert.Der Datenpool zum Radiohören in der DDR umfasst 51 Studien und deckt einen Zeitraum von 1980-1989 ab. Die Studien sind unter den ZA- Nrn. ZA6500 - ZA6550 archiviert.      </text>    </note>  </notes>  <principalInvestigators>    <principalInvestigator id="88455">      <affiliation>        Staatliches Komitee für Fernsehen beim Ministerrat der DDR, Abteilung Soziologische Forschung, Berlin      </affiliation>      <name>              </name>    </principalInvestigator>  </principalInvestigators>  <priorVersions />  <publicationAgent id="2447">    <contactPerson>      Brigitte Hausstein    </contactPerson>    <email>      Brigitte.Hausstein@gesis.org    </email>    <homepage>      http://www.gesis.org/    </homepage>    <logo>      /dara/fileadmin/doi/Dateien/GESIS_Logo_51x20.jpg    </logo>    <name>      GESIS - Leibniz-Institut für Sozialwissenschaften    </name>    <prefix />    <suffixstart />  </publicationAgent>  <publicationDate />  <publicationPlace />  <publications />  <regAgency id="2443">    <contactPerson>      Brigitte Hausstein    </contactPerson>    <email>      Brigitte.Hausstein@gesis.org    </email>    <homepage>      http://www.gesis.org    </homepage>    <name>      GESIS - Leibniz-Institut für Sozialwissenschaften    </name>  </regAgency>  <relatedIDs />  <rights />  <selectionMethods>    <selectionMethod id="146010">      <language>        de      </language>      <method>        Repräsentative Haushaltsstichprobe: Geschichtete Zufallsauswahl; Zufallsadresse aus der Fernsehteilnehmerkartei der Deutschen Post.      </method>      <study ref="../.." />    </selectionMethod>  </selectionMethods>  <sizes />  <studyId>    ZA7311  </studyId>  <summary>    <summary id="146005">      <language>        de      </language>      <study ref="../.." />      <text>        Zuschauerbeteiligung und Fernsehverhalten.Themen: Sehbeteiligung und Bewertung der Sendungen in der Woche vor der Befragung; Zusatzfragen: Innerliche Berührung durch die Geschichte im Fernsehfilm WIR SIND FÜNF; Sympathie für die Hauptfiguren und Gründe dafür; Aspekte des Films, welche ihn sehenswert machen; Bewertung des Gastgebers der Sendung SHOWKOLADE und Meinung zur Sendung; Meinung zum Schwank FERIENHEIM BERGKRISTALL (5): SO EIN THEATER; Bewertung des Humors der Sendung TEMPO 88; Bewertung der Moderatoren der Silvestersendung; Zufriedenheit mit der Sendung JAHRESRÜCKBLICK DER AKTUELLEN KAMERA 1987; Rezeption der Sendung SPUK VON DRAUSSEN; Gefallen des Humors und einzelner Aspekte der Sendung; Gefallen einzelner Aspekte des Jahresendprogramms und des Silvesterprogramms. Demographie: Haushaltsgröße; Alter; Geschlecht; Schulbildung; Tätigkeit; Weiterbildung; Neuerertätigkeit; Parteimitgliedschaft; Ehrenamt; Empfangsbedingungen.      </text>    </summary>  </summary>  <titles>    <title id="146003">      <language>        en      </language>      <study ref="../.." />      <title>        Sofortresonanzen DDR Fernsehen 1. Woche 1988 (SFR 1/88)      </title>    </title>    <title id="146004">      <language>        de      </language>      <study ref="../.." />      <title>        Sofortresonanzen DDR Fernsehen 1. Woche 1988 (SFR 1/88)      </title>    </title>  </titles>  <translatedTitles />  <universes>    <universe id="146012">      <areaControlled>              </areaControlled>      <areaFree>        Wohnbevölkerung der DDR (registrierte Fernsehteilnehmer) Einbeziehung aller Personen des Haushaltes ab 4. Lebensjahr, Zusatzfragen nur an Personen ab 14. Lebensjahr.      </areaFree>      <language>        de      </language>      <study ref="../.." />      <universe>        Wohnbevölkerung der DDR (registrierte Fernsehteilnehmer) Einbeziehung aller Personen des Haushaltes ab 4. Lebensjahr, Zusatzfragen nur an Personen ab 14. Lebensjahr.      </universe>    </universe>    <universe id="146011">      <areaControlled>              </areaControlled>      <areaFree>        Resident population of the GDR (TV registered participants)      </areaFree>      <language>        en      </language>      <study ref="../.." />      <universe>        Resident population of the GDR (TV registered participants)      </universe>    </universe>  </universes>  <urls>    <dataURL id="146001">      <dataURL>        http://info1.gesis.org/dbksearch/sdesc2.asp?no=7311&amp;db=e&amp;doi=10.4232/1.10552      </dataURL>      <study ref="../.." />    </dataURL>  </urls></study>